dsresumatch/__init__.py
dsresumatch/data/baseline_keywords.json
dsresumatch/evaluate_keywords.py
dsresumatch/pdf_cv_processing.py
dsresumatch/resume_scoring.py
dsresumatch/sections_check.py
dsresumatch-1.1.8.dist-info/LICENSE
dsresumatch-1.1.8.dist-info/METADATA
dsresumatch-1.1.8.dist-info/WHEEL
dsresumatch-1.1.8.dist-info/RECORD
