Metadata-Version: 2.3
Name: dsresumatch
Version: 1.1.8
Summary: Analyze resumes and job descriptions by extracting key sections and scoring them based on keyword relevance
License: MIT
Author: Nelli Hovhannisyan, Ashita Diwan, Timothy Singh,Jia Quan Lim
Requires-Python: >=3.11
Classifier: License :: OSI Approved :: MIT License
Classifier: Programming Language :: Python :: 3
Classifier: Programming Language :: Python :: 3.11
Classifier: Programming Language :: Python :: 3.12
Classifier: Programming Language :: Python :: 3.13
Requires-Dist: nltk (>=3.9.1)
Requires-Dist: pypdf2 (>=3.0.1)
